README.rst
setup.cfg
setup.py
custos/__init__.py
custos.egg-info/PKG-INFO
custos.egg-info/SOURCES.txt
custos.egg-info/dependency_links.txt
custos.egg-info/not-zip-safe
custos.egg-info/requires.txt
custos.egg-info/top_level.txt
custos/checks/__init__.py
custos/notify/__init__.py
custos/notify/base.py
custos/notify/console.py
custos/notify/http.py
custos/notify/levels.py
custos/notify/log.py
custos/notify/message.py
custos/notify/smtp.py
custos/notify/telegram.py
custos/notify/twilio.py