Metadata-Version: 1.0
Name: custos
Version: 0.0.6
Summary: A framework for monitoring and notifying
Home-page: https://github.com/fact-project/pycustos
Author: Dominik Neise, Maximilian Noethe, Sebastian Mueller
Author-email: maximilian.noethe@tu-dortmund.de
License: MIT
Platform: UNKNOWN
